loggo2/__init__.py
loggo2/_loggo2.py
loggo2/py.typed
loggo2-10.1.3.dist-info/LICENSE
loggo2-10.1.3.dist-info/METADATA
loggo2-10.1.3.dist-info/WHEEL
loggo2-10.1.3.dist-info/top_level.txt
loggo2-10.1.3.dist-info/RECORD
