Metadata-Version: 2.1
Name: loggo2
Version: 10.1.3
Summary: Python logging tools
Home-page: https://github.com/bitpanda-labs/loggo2
Author: Bitpanda GmbH
Author-email: nosupport@bitpanda.com
License: MIT
Project-URL: Changelog, https://github.com/bitpanda-labs/loggo2/blob/master/CHANGELOG.md
Keywords: bitpanda utilities logging
Classifier: Topic :: Utilities
Classifier: Typing :: Typed
Classifier: License :: OSI Approved :: MIT License
Classifier: Programming Language :: Python :: 3 :: Only
Classifier: Programming Language :: Python :: 3.9
Requires-Python: >=3.9
License-File: LICENSE
Requires-Dist: typing-extensions (<5.0.0,>=4.2.0) ; python_version >= "3.9"
Provides-Extra: dev
Requires-Dist: graypy (<3.0.0,>=2.0.0) ; extra == 'dev'
Requires-Dist: pytest ; extra == 'dev'
Requires-Dist: pytest-randomly ; extra == 'dev'
Requires-Dist: pytest-cov ; extra == 'dev'
Requires-Dist: isort ; extra == 'dev'
Requires-Dist: black ; extra == 'dev'
Requires-Dist: flake8 ; extra == 'dev'
Requires-Dist: flake8-bugbear ; extra == 'dev'
Requires-Dist: flake8-builtins ; extra == 'dev'
Requires-Dist: flake8-comprehensions ; extra == 'dev'
Requires-Dist: mypy ; extra == 'dev'
Requires-Dist: docformatter ; extra == 'dev'
Requires-Dist: pre-commit ; extra == 'dev'
Requires-Dist: codecov ; extra == 'dev'
Requires-Dist: bump2version ; extra == 'dev'
Provides-Extra: graylog
Requires-Dist: graypy (<3.0.0,>=2.0.0) ; extra == 'graylog'
Provides-Extra: lint
Requires-Dist: isort ; extra == 'lint'
Requires-Dist: black ; extra == 'lint'
Requires-Dist: flake8 ; extra == 'lint'
Requires-Dist: flake8-bugbear ; extra == 'lint'
Requires-Dist: flake8-builtins ; extra == 'lint'
Requires-Dist: flake8-comprehensions ; extra == 'lint'
Requires-Dist: mypy ; extra == 'lint'
Requires-Dist: docformatter ; extra == 'lint'
Requires-Dist: pre-commit ; extra == 'lint'
Provides-Extra: tests
Requires-Dist: pytest ; extra == 'tests'
Requires-Dist: pytest-randomly ; extra == 'tests'
Requires-Dist: pytest-cov ; extra == 'tests'
Provides-Extra: tools
Requires-Dist: codecov ; extra == 'tools'
Requires-Dist: bump2version ; extra == 'tools'
